CHANGES.rst
LICENSE
MANIFEST.in
README.rst
pyproject.toml
requirements.txt
setup.py
docs/Makefile
docs/conf.py
docs/index.rst
docs/modules/chat.rst
docs/modules/modules.rst
docs/modules/outputvideo.rst
docs/modules/twitchstream.rst
examples/__init__.py
examples/basic_chat.py
examples/basic_video_out.py
examples/color.py
twitchchatget.egg-info/PKG-INFO
twitchchatget.egg-info/SOURCES.txt
twitchchatget.egg-info/dependency_links.txt
twitchchatget.egg-info/not-zip-safe
twitchchatget.egg-info/requires.txt
twitchchatget.egg-info/top_level.txt
twitchstream/__init__.py
twitchstream/chat.py
twitchstream/exceptions.py
twitchstream/outputvideo.py
twitchstream/tests/conftest.py
twitchstream/tests/test_chat.py
twitchstream/tests/test_inputvideo.py
twitchstream/tests/test_outputvideo.py